honeycomb/__init__.py
honeycomb/__main__.py
honeycomb/cli.py
honeycomb/defs.py
honeycomb/error_messages.py
honeycomb/exceptions.py
honeycomb/commands/__init__.py
honeycomb/commands/integration/__init__.py
honeycomb/commands/integration/configure.py
honeycomb/commands/integration/install.py
honeycomb/commands/integration/list.py
honeycomb/commands/integration/show.py
honeycomb/commands/integration/test.py
honeycomb/commands/integration/uninstall.py
honeycomb/commands/service/__init__.py
honeycomb/commands/service/install.py
honeycomb/commands/service/list.py
honeycomb/commands/service/logs.py
honeycomb/commands/service/run.py
honeycomb/commands/service/show.py
honeycomb/commands/service/status.py
honeycomb/commands/service/stop.py
honeycomb/commands/service/test.py
honeycomb/commands/service/uninstall.py
honeycomb/decoymanager/__init__.py
honeycomb/decoymanager/models.py
honeycomb/integrationmanager/__init__.py
honeycomb/integrationmanager/defs.py
honeycomb/integrationmanager/error_messages.py
honeycomb/integrationmanager/exceptions.py
honeycomb/integrationmanager/integration_utils.py
honeycomb/integrationmanager/models.py
honeycomb/integrationmanager/registration.py
honeycomb/integrationmanager/tasks.py
honeycomb/servicemanager/__init__.py
honeycomb/servicemanager/base_service.py
honeycomb/servicemanager/defs.py
honeycomb/servicemanager/error_messages.py
honeycomb/servicemanager/exceptions.py
honeycomb/servicemanager/models.py
honeycomb/servicemanager/registration.py
honeycomb/utils/__init__.py
honeycomb/utils/config_utils.py
honeycomb/utils/daemon.py
honeycomb/utils/plugin_utils.py
honeycomb/utils/tailer.py
honeycomb/utils/validators.py
honeycomb/utils/wait.py
tests/utils/__init__.py
tests/utils/defs.py
tests/utils/syslog.py
tests/utils/test_utils.py
honeycomb_framework-0.1.1.dist-info/LICENSE
honeycomb_framework-0.1.1.dist-info/METADATA
honeycomb_framework-0.1.1.dist-info/WHEEL
honeycomb_framework-0.1.1.dist-info/entry_points.txt
honeycomb_framework-0.1.1.dist-info/top_level.txt
honeycomb_framework-0.1.1.dist-info/RECORD
