Metadata-Version: 2.1
Name: honeycomb-framework
Version: 0.1.1
Summary: Honeycomb is a honeypot framework
Home-page: https://github.com/Cymmetria/honeycomb
Author: Honeycomb - Honeypot Framework
Author-email: omer.cohen@cymmetria.com
License: MIT
Platform: any
Classifier: Development Status :: 4 - Beta
Classifier: Environment :: Console
Classifier: Intended Audience :: Developers
Classifier: License :: OSI Approved :: MIT License
Classifier: Operating System :: POSIX
Classifier: Operating System :: MacOS
Classifier: Operating System :: Unix
Classifier: Operating System :: Microsoft :: Windows
Classifier: Programming Language :: Python
Classifier: Programming Language :: Python :: 2
Classifier: Programming Language :: Python :: 3
Classifier: Topic :: Software Development :: Libraries :: Python Modules
Requires-Dist: six (~=1.11)
Requires-Dist: click (==7.0)
Requires-Dist: attrs (==18.2.0)
Requires-Dist: PyYAML (==3.13)
Requires-Dist: requests (==2.20.1)
Requires-Dist: python-daemon (==2.2.0)
Requires-Dist: python-json-logger (==0.1.10)
Requires-Dist: docker (==3.6.0)
